{"duration": 4.248398780822754, "input_args": {"imgs": "<nibabel.nifti1.Nifti1Image object at 0x1c2ca0c4e0>", "extraction_function": "<nilearn.input_data.nifti_labels_masker._ExtractionFunctor object at 0x1c2de805f8>", "parameters": "{'background_label': 0, 'detrend': True, 'dtype': None, 'high_pass': 0.009, 'labels_img': <nibabel.nifti1.Nifti1Image object at 0x1c2e1e4630>, 'low_pass': 0.08, 'mask_img': None, 'smoothing_fwhm': None, 'standardize': False, 'strategy': 'mean', 't_r': 2, 'target_shape': None, 'target_affine': None}", "confounds": "[array([[-6.70685053e-01,  2.70725346e+00,  6.53850500e-01, ...,\n         3.12237000e-04, -1.24479000e-23,  2.29624000e-04],\n       [ 1.11505747e+00,  3.05961084e+00,  6.68611590e-01, ...,\n         5.41360000e-04,  5.91557000e-04, -2.60792000e-05],\n       [-5.73809624e-01,  6.46465302e-01,  1.08950782e+00, ...,\n         1.22786000e-03,  8.74730000e-04,  3.42675000e-04],\n       ...,\n       [ 2.31035757e+00,  4.70277929e+00,  6.32941070e-01, ...,\n        -2.22308000e-04, -5.03974000e-03, -1.93866000e-03],\n       [ 3.45138574e+00,  4.92421627e+00,  6.64833430e-01, ...,\n        -8.54937000e-04, -5.40071000e-03, -2.26633000e-03],\n       [-7.25432682e+00, -1.26366959e+01,  2.17750597e+00, ...,\n         8.56623000e-04, -5.00081000e-03, -7.60386000e-04]])]", "copy": "True", "dtype": "None"}}