{"duration": 3.753365993499756, "input_args": {"imgs": "<nibabel.nifti1.Nifti1Image object at 0x1c25ee5ac8>", "extraction_function": "<nilearn.input_data.nifti_labels_masker._ExtractionFunctor object at 0x120de3c50>", "parameters": "{'background_label': 0, 'detrend': True, 'dtype': None, 'high_pass': 0.009, 'labels_img': <nibabel.nifti1.Nifti1Image object at 0x1c25e1d780>, 'low_pass': 0.08, 'mask_img': None, 'smoothing_fwhm': None, 'standardize': False, 'strategy': 'mean', 't_r': 2, 'target_shape': None, 'target_affine': None}", "confounds": "[array([[-4.87152010e-01,  7.91160882e-01,  1.25438952e+00, ...,\n        -1.95773000e-03, -4.48294000e-04,  6.61357000e-04],\n       [-7.73073077e-01,  5.20855546e-01,  1.09697199e+00, ...,\n        -2.38801000e-03, -8.79364000e-22,  1.01384000e-03],\n       [-7.21591711e-01, -2.09952593e-02,  1.12047362e+00, ...,\n        -3.19468000e-03, -3.96505000e-04,  8.85672000e-04],\n       ...,\n       [ 7.01311529e-02, -1.39568895e-01,  1.15686965e+00, ...,\n         9.20128000e-04,  3.02457000e-03, -1.53579000e-03],\n       [-1.87069714e+00, -9.48326409e-01,  1.15140450e+00, ...,\n         1.73393000e-03,  3.03431000e-03, -1.59275000e-03],\n       [-5.30414879e-02,  2.22198105e+00,  1.16211641e+00, ...,\n         5.37652000e-04,  2.91750000e-03, -1.85769000e-03]])]", "copy": "True", "dtype": "None"}}